LICENSE
pg_logger/__init__.py
pg_logger/_config.py
pg_logger/_file.py
pg_logger/_handler.py
pg_logger/_logger.py
pg_logger/_style.py
pg_logger/_traceback.py
pg_logger/_typedefs.py
paigram_logger-0.0.2.dist-info/LICENSE
paigram_logger-0.0.2.dist-info/METADATA
paigram_logger-0.0.2.dist-info/WHEEL
paigram_logger-0.0.2.dist-info/RECORD
