Metadata-Version: 2.1
Name: paigram-logger
Version: 0.0.2
Summary: A logger for PaiGram's projects.
Home-page: https://github.com/PaiGramTeam/paigram-logger
License: MIT
Author: Karako
Author-email: karakohear@gmail.com
Requires-Python: >=3.8,<4.0
Classifier: License :: OSI Approved :: MIT License
Classifier: Programming Language :: Python :: 3
Classifier: Programming Language :: Python :: 3.8
Classifier: Programming Language :: Python :: 3.9
Classifier: Programming Language :: Python :: 3.10
Classifier: Programming Language :: Python :: 3.11
Classifier: Programming Language :: Python :: 3 :: Only
Classifier: Programming Language :: Python :: 3.10
Classifier: Programming Language :: Python :: 3.11
Classifier: Programming Language :: Python :: 3.8
Classifier: Programming Language :: Python :: 3.9
Classifier: Programming Language :: Python :: Implementation :: CPython
Classifier: Topic :: Software Development :: Libraries :: Python Modules
Requires-Dist: pydantic[dotenv] (>=1.10.7,<2.0.0)
Requires-Dist: rich (>=13.3.0,<14.0.0)
